setup.py
d2d/__init__.py
d2d/frame.py
d2d/runserver.py
d2d.egg-info/PKG-INFO
d2d.egg-info/SOURCES.txt
d2d.egg-info/dependency_links.txt
d2d.egg-info/top_level.txt