Metadata-Version: 1.1
Name: d2d
Version: 0.7
Summary: Deploy Django application on desktop window.
Home-page: UNKNOWN
Author: Yeison Cardona
Author-email: yeison.eng@gmail.com
License: BSD License
Platform: UNKNOWN
Classifier: Environment :: Web Environment
Classifier: Framework :: Django
